layernode/__init__.py
layernode/api.py
layernode/blockchain.py
layernode/cli.py
layernode/client_db.py
layernode/custom.py
layernode/database.py
layernode/engine.py
layernode/evm_scan.py
layernode/layer_core.py
layernode/models.py
layernode/my_ipfs.py
layernode/peer_check.py
layernode/peer_listen.py
layernode/service.py
layernode/state.py
layernode/tools.py
layernode/ntwrk/__init__.py
layernode/ntwrk/message.py
layernode/ntwrk/response.py
Layernode-0.0.3.dist-info/LICENSE
Layernode-0.0.3.dist-info/METADATA
Layernode-0.0.3.dist-info/WHEEL
Layernode-0.0.3.dist-info/entry_points.txt
Layernode-0.0.3.dist-info/top_level.txt
Layernode-0.0.3.dist-info/RECORD
