Metadata-Version: 2.1
Name: Layernode
Version: 0.0.3
Summary: LayerProtocol blockchain
Home-page: https://github.com/LayerProtocol/layernode.git
Author: NoRestLabs
Author-email: galen@norestlabs.com
License: UNKNOWN
Platform: UNKNOWN
Classifier: Development Status :: 2 - Pre-Alpha
Classifier: Intended Audience :: Developers
Classifier: License :: OSI Approved :: MIT License
Classifier: Natural Language :: English
Classifier: Programming Language :: Python :: 3
Classifier: Programming Language :: Python :: 3.5
Classifier: Programming Language :: Python :: 3.6
Requires-Dist: altgraph
Requires-Dist: dnspython
Requires-Dist: wheel
Requires-Dist: pyyaml
Requires-Dist: flask
Requires-Dist: flask-socketio
Requires-Dist: m3-cdecimal
Requires-Dist: pyopenssl
Requires-Dist: werkzeug
Requires-Dist: tabulate
Requires-Dist: ecdsa
Requires-Dist: plyvel
Requires-Dist: layer-py
Requires-Dist: enum-compat
Requires-Dist: eventlet
Requires-Dist: future
Requires-Dist: greenlet
Requires-Dist: ipfsapi
Requires-Dist: macholib
Requires-Dist: pefile
Requires-Dist: psutil
Requires-Dist: PyInstaller
Requires-Dist: PyMySQL
Requires-Dist: python-slugify
Requires-Dist: requests-toolbelt
Requires-Dist: simplekv
Requires-Dist: SQLAlchemy
Requires-Dist: Unidecode
Requires-Dist: websocket-client
